MITREAttackScrapper/__init__.py
MITREAttackScrapper/enterprise_techniques.py
MITREAttackScrapper/superclass.py
MITREAttackScrapper/cti/__init__.py
MITREAttackScrapper/cti/campaigns.py
MITREAttackScrapper/cti/groups.py
MITREAttackScrapper/cti/software.py
MITREAttackScrapper/matrices/__init__.py
MITREAttackScrapper/matrices/enterprise.py
MITREAttackScrapper/mitigations/__init__.py
MITREAttackScrapper/mitigations/enterprise.py
MITREAttackScrapper/tactics/__init__.py
MITREAttackScrapper/tactics/enterprise.py
MITREAttackScrapper/techniques/__init__.py
MITREAttackScrapper/techniques/enterprise.py
MITREAttackScrapper/utils/__init__.py
MITREAttackScrapper/utils/mitre_id_validator.py
MITREAttackScrapper/utils/scrapping_helper.py
MITREAttackScrapper-0.1.5.dist-info/METADATA
MITREAttackScrapper-0.1.5.dist-info/WHEEL
MITREAttackScrapper-0.1.5.dist-info/top_level.txt
MITREAttackScrapper-0.1.5.dist-info/RECORD
