Metadata-Version: 2.1
Name: MITREAttackScrapper
Version: 0.1.5
Summary: A package for conveniently retrieving MITRE ATT&CK data
Home-page: https://github.com/KnightChaser/MITREAttackScrapper
Author: KnightChaser
Author-email: agerio100@naver.com
Classifier: Programming Language :: Python :: 3
Classifier: License :: OSI Approved :: MIT License
Classifier: Operating System :: OS Independent
Requires-Python: >=3.6
Requires-Dist: beautifulsoup4
Requires-Dist: httpx
Requires-Dist: pandas
